Metadata-Version: 2.1
Name: egensdytcfydtfduyscfstcfy
Version: 1.0
Summary: Опис проєкту
Author: Kirill
Author-email: 123@gmail.com
